app/tools.py
bond_analysis_tools-0.1.2.dist-info/METADATA
bond_analysis_tools-0.1.2.dist-info/WHEEL
bond_analysis_tools-0.1.2.dist-info/entry_points.txt
bond_analysis_tools-0.1.2.dist-info/top_level.txt
bond_analysis_tools-0.1.2.dist-info/RECORD
