Metadata-Version: 2.4
Name: bond-analysis-tools
Version: 0.1.2
Summary: A toolset for convertible bond arbitrage analysis using akshare and mcp-sdk.
Requires-Python: >=3.10
Requires-Dist: akshare
Requires-Dist: mcp
Requires-Dist: fastapi
Requires-Dist: uvicorn[standard]
Requires-Dist: pandas
Requires-Dist: lru-cache
